airflow_indexima/__init__.py
airflow_indexima/connection.py
airflow_indexima/hive_transport.py
airflow_indexima/hooks/__init__.py
airflow_indexima/hooks/indexima.py
airflow_indexima/indexima.py
airflow_indexima/operators/__init__.py
airflow_indexima/operators/indexima.py
airflow_indexima/uri/__init__.py
airflow_indexima/uri/factory.py
airflow_indexima/uri/jdbc.py
airflow_indexima-2.2.1.dist-info/entry_points.txt
airflow_indexima-2.2.1.dist-info/LICENSE.md
airflow_indexima-2.2.1.dist-info/WHEEL
airflow_indexima-2.2.1.dist-info/METADATA
airflow_indexima-2.2.1.dist-info/RECORD
