Metadata-Version: 2.1
Name: airflow-indexima
Version: 2.2.1
Summary: Indexima Airflow integration
Home-page: https://pypi.org/project/airflow_indexima
License: MIT
Author: Jerome Guibert
Author-email: jguibert@gmail.com
Requires-Python: >=3.6,<4.0
Classifier: Development Status :: 5 - Production/Stable
Classifier: Intended Audience :: Developers
Classifier: License :: OSI Approved :: MIT License
Classifier: Natural Language :: English
Classifier: Programming Language :: Python
Classifier: Programming Language :: Python :: 3
Classifier: Programming Language :: Python :: 3.6
Classifier: Programming Language :: Python :: 3.7
Classifier: Topic :: Software Development :: Libraries :: Python Modules
Classifier: Typing :: Typed
Requires-Dist: PyHive (==0.6.1)
Requires-Dist: apache-airflow (==1.10.2)
Requires-Dist: gitpython (>=2.1.0,<2.2.0)
Requires-Dist: thrift (>=0.13.0,<0.14.0)
Requires-Dist: thrift-sasl (==0.3.0)
Project-URL: Documentation, https://geronimo-iia.github.io/airflow-indexima/
Project-URL: Repository, https://github.com/geronimo-iia/airflow-indexima
